LICENSE
README.md
setup.cfg
setup.py
wordlyzer3/__init__.py
wordlyzer3/wordlyzer.py
wordlyzer3.egg-info/PKG-INFO
wordlyzer3.egg-info/SOURCES.txt
wordlyzer3.egg-info/dependency_links.txt
wordlyzer3.egg-info/requires.txt
wordlyzer3.egg-info/top_level.txt