Metadata-Version: 2.1
Name: wordlyzer3
Version: 0.3
Summary: A simple library for text analysis
Home-page: https://github.com/NuricoVicyyanto/wordlyzer.git
Download-URL: https://github.com/nuricovicyyanto/wordlyzer/archive/v_01.tar.gz
Author: Nurico Vicyyanto
Author-email: nuricovicyyanto@gmail.com
License: MIT
Project-URL: Documentation, https://packaging.python.org/tutorials/distributing-packages/
Project-URL: Funding, https://donate.pypi.org
Project-URL: Say Thanks!, http://saythanks.io/to/nuricovicyyanto
Project-URL: Source, https://github.com/nuricovicyyanto/wordlyzer
Project-URL: Tracker, https://github.com/nuricovicyyanto/wordlyzer/issues
Keywords: text,analysis,python,library
Classifier: Development Status :: 3 - Alpha
Classifier: Intended Audience :: Developers
Classifier: Topic :: Software Development :: Libraries
Classifier: License :: OSI Approved :: MIT License
Classifier: Programming Language :: Python :: 3
Classifier: Programming Language :: Python :: 3.7
Classifier: Programming Language :: Python :: 3.8
Classifier: Programming Language :: Python :: 3.9
Classifier: Programming Language :: Python :: 3.10
Classifier: Programming Language :: Python :: 3.11
License-File: LICENSE
Requires-Dist: validators
Requires-Dist: beautifulsoup4
